langchain_ydb/__init__.py
langchain_ydb/py.typed
langchain_ydb/vectorstores.py
langchain_ydb-0.0.11.dist-info/METADATA
langchain_ydb-0.0.11.dist-info/WHEEL
langchain_ydb-0.0.11.dist-info/licenses/LICENSE
langchain_ydb-0.0.11.dist-info/RECORD
