Metadata-Version: 2.4
Name: langchain-ydb
Version: 0.0.11
Summary: An integration package connecting YDB and LangChain
License-File: LICENSE
Keywords: ydb,langchain,database,AI
Requires-Python: >=3.9,<4.0
Classifier: Programming Language :: Python :: 3
Classifier: Programming Language :: Python :: 3.9
Classifier: Programming Language :: Python :: 3.10
Classifier: Programming Language :: Python :: 3.11
Classifier: Programming Language :: Python :: 3.12
Classifier: Programming Language :: Python :: 3.13
Classifier: Programming Language :: Python :: 3.14
Requires-Dist: langchain-core (>=0.2.13,<0.4.0)
Requires-Dist: ydb-dbapi (>=0.1.11,<0.2.0)
